nvector-1.0.1.dist-info/METADATA
nvector-1.0.1.dist-info/WHEEL
nvector-1.0.1.dist-info/entry_points.txt
nvector-1.0.1.dist-info/licenses/LICENSE.txt
nvector/__init__.py
nvector/_acknowledgements.py
nvector/_common.py
nvector/_documentation.py
nvector/_examples.py
nvector/_examples_object_oriented.py
nvector/_images.py
nvector/_info.py
nvector/_info_functional.py
nvector/_installation.py
nvector/_intro.py
nvector/_license.py
nvector/_typing.py
nvector/core.py
nvector/objects.py
nvector/plot.py
nvector/rotation.py
nvector/tests/__init__.py
nvector/tests/conftest.py
nvector/tests/test_geodesic.py
nvector/tests/test_nvector.py
nvector/tests/test_nvector_with_vectors.py
nvector/tests/test_objects.py
nvector/tests/test_plot.py
nvector/tests/test_rotation.py
nvector/tests/test_util.py
nvector/util.py
nvector-1.0.1.dist-info/RECORD
